slow_trading_agent/__init__.py
slow_trading_agent/api_application_helper.py
slow_trading_agent/api_config.py
slow_trading_agent/api_config_template.py
slow_trading_agent/bailian_mcp_entry.py
slow_trading_agent/enhanced_real_data_tools.py
slow_trading_agent/main.py
slow_trading_agent/quick_token_analysis.py
slow_trading_agent/robust_mcp_server.py
slow_trading_agent/standalone_mcp_server.py
slow_trading_agent/controller/__init__.py
slow_trading_agent/controller/slow_trading_controller.py
slow_trading_agent/core/__init__.py
slow_trading_agent/core/agent_executor.py
slow_trading_agent/core/agent_prompt.py
slow_trading_agent/core/streamlined_agent_prompt.py
slow_trading_agent/memory/__init__.py
slow_trading_agent/memory/analysis_memory.py
slow_trading_agent/tools/__init__.py
slow_trading_agent/tools/data_query_tools.py
slow_trading_agent/tools/memory_tools.py
slow_trading_agent/tools/narrative_scoring_tools.py
slow_trading_agent/tools/optimistic_scoring_tools.py
slow_trading_agent/tools/real_data_tools.py
slow_trading_agent/tools/risk_assessment_tools.py
slow_trading_agent/tools/sentiment_analysis_tools.py
memecoin_analyst_agent-0.1.9.dist-info/METADATA
memecoin_analyst_agent-0.1.9.dist-info/WHEEL
memecoin_analyst_agent-0.1.9.dist-info/entry_points.txt
memecoin_analyst_agent-0.1.9.dist-info/top_level.txt
memecoin_analyst_agent-0.1.9.dist-info/RECORD
