Metadata-Version: 2.4
Name: memecoin-analyst-agent
Version: 0.1.9
Summary: Memecoin Smart Trading Analyst Agent with MCP server for Alibaba Cloud Bailian
Author: Memecoin Trading Team
License: MIT
Project-URL: Homepage, https://github.com/memecoin-trading/agent
Keywords: mcp,agent,memecoin,bsc,web3,analysis
Requires-Python: >=3.8
Requires-Dist: langchain>=0.1.0
Requires-Dist: langchain-openai>=0.1.0
Requires-Dist: langchain-community>=0.1.0
Requires-Dist: openai>=1.0.0
Requires-Dist: requests>=2.28.0
Requires-Dist: httpx>=0.24.0
Requires-Dist: aiohttp>=3.8.0
Requires-Dist: pydantic>=2.0.0
